widen/__init__.py
widen/__main__.py
widen/basics/__init__.py
widen/basics/animals/Octopus.py
widen/basics/animals/__init__.py
widen/basics/animals/__main__.py
widen/basics/animals/args.py
widen/basics/animals/cow.py
widen/basics/animals/models.py
widen/basics/animals/snek.py
widen/basics/distributions/Binomialdistribution.py
widen/basics/distributions/Gaussiandistribution.py
widen/basics/distributions/Generaldistribution.py
widen/basics/distributions/__init__.py
widen/basics/utils/__init__.py
widen/basics/utils/hello.py
widen/basics/utils/prints.py
widen/cli/__init__.py
widen/cli/cli.py
widen/data/addresses.csv
widen/data/numbers.txt
widen/data/numbers_binomial.txt
widen/data/test.tx2
widen-0.0.1.dev0.dist-info/LICENSE.txt
widen-0.0.1.dev0.dist-info/METADATA
widen-0.0.1.dev0.dist-info/WHEEL
widen-0.0.1.dev0.dist-info/entry_points.txt
widen-0.0.1.dev0.dist-info/top_level.txt
widen-0.0.1.dev0.dist-info/RECORD
